Workbook

Sheet Raw Data& 2.1.1
A1: Retailer | B1: Retailer ID | C1: Invoice Date | D1: Region | E1: State | F1: City | G1: Product | H1: Price per Unit | I1: Units Sold | J1: Total Sales | K1: Operating Profit | L1: Sales Method
A2: Walmart | B2: 1128299 | C2: 44364 | D2: Southeast | E2: Florida | F2: Orlando | G2: Women's Apparel | H2: 103 | I2: 218 | J2: 2245 | K2: 1257 | L2: Online
A3: West Gear | B3: 1128299 | C3: 44393 | D3: South | E3: Louisiana | F3: New Orleans | G3: Women's Apparel | H3: 103 | I3: 163 | J3: 1679 | K3: 806 | L3: Online | N3: Table 2.1.1(Region)
A4: Sports Direct | B4: 1197831 | C4: 44433 | D4: South | E4: Alabama | F4: Birmingham | G4: Men's Street Footwear | H4: 10 | I4: 700 | J4: 7000 | K4: 3150 | L4: Outlet | N4: Region | O4: Frequency | P4: Relative Frequency | Q4: Cumulative Frequency | R4: Cumulative Relative Frequency
A5: Sports Direct | B5: 1197831 | C5: 44435 | D5: South | E5: Alabama | F5: Birmingham | G5: Women's Street Footwear | H5: 15 | I5: 575 | J5: 8625 | K5: 3881 | L5: Outlet | N5: {=_xlfn.UNIQUE(D2:D5000)} -> Southeast | O5: =COUNTIF($D$2:$D$5000,"Southeast") -> 650 | P5: =O5/SUM($O$5:$O$9) -> 0.13002601 | Q5: =O5 -> 650 | R5: =Q5/SUM($O$5:$O$9) -> 0.13002601
A6: Sports Direct | B6: 1197831 | C6: 44429 | D6: South | E6: Alabama | F6: Birmingham | G6: Women's Street Footwear | H6: 15 | I6: 475 | J6: 7125 | K6: 3206 | L6: Outlet | N6: South | O6: =COUNTIF($D$2:$D$5000,"South") -> 1130 | P6: =O6/SUM($O$5:$O$9) -> 0.22604521 | Q6: =O5+O6 -> 1780 | R6: =Q6/SUM($O$5:$O$9) -> 0.35607121
A7: West Gear | B7: 1185732 | C7: 44207 | D7: Midwest | E7: Missouri | F7: St. Louis | G7: Women's Street Footwear | H7: 15 | I7: 475 | J7: 7125 | K7: 2494 | L7: In-store | N7: Midwest | O7: =COUNTIF($D$2:$D$5000,"Midwest") -> 809 | P7: =O7/SUM($O$5:$O$9) -> 0.16183237 | Q7: =SUM(O5:O7) -> 2589 | R7: =Q7/SUM($O$5:$O$9) -> 0.51790358
A8: Sports Direct | B8: 1185732 | C8: 44517 | D8: South | E8: Mississippi | F8: Jackson | G8: Men's Athletic Footwear | H8: 20 | I8: 450 | J8: 9000 | K8: 3150 | L8: Online | N8: Northeast | O8: =COUNTIF($D$2:$D$5000,"Northeast") -> 1001 | P8: =O8/SUM($O$5:$O$9) -> 0.20024005 | Q8: =SUM(O5:O8) -> 3590 | R8: =Q8/SUM($O$5:$O$9) -> 0.71814363
A9: Sports Direct | B9: 1197831 | C9: 44219 | D9: South | E9: Mississippi | F9: Jackson | G9: Women's Street Footwear | H9: 15 | I9: 450 | J9: 6750 | K9: 2700 | L9: Online | N9: West | O9: =COUNTIF($D$2:$D$5000,"West") -> 1409 | P9: =O9/SUM($O$5:$O$9) -> 0.28185637 | Q9: =SUM(O5:O9) -> 4999 | R9: =Q9/SUM($O$5:$O$9) -> 1
A10: West Gear | B10: 1185732 | C10: 44289 | D10: Midwest | E10: Wisconsin | F10: Milwaukee | G10: Men's Street Footwear | H10: 20 | I10: 450 | J10: 9000 | K10: 2700 | L10: In-store
A11: Foot Locker | B11: 1185732 | C11: 43900 | D11: Northeast | E11: New York | F11: New York | G11: Men's Street Footwear | H11: 44 | I11: 434 | J11: 1910 | K11: 993 | L11: Outlet
A12: Foot Locker | B12: 1185732 | C12: 44214 | D12: Midwest | E12: Michigan | F12: Detroit | G12: Women's Street Footwear | H12: 20 | I12: 425 | J12: 8500 | K12: 2975 | L12: In-store | N12: Table 2.1.1(Sales Method)
A13: West Gear | B13: 1185732 | C13: 44238 | D13: Midwest | E13: Missouri | F13: St. Louis | G13: Women's Street Footwear | H13: 15 | I13: 425 | J13: 6375 | K13: 2231 | L13: In-store | N13: Region | O13: Frequency | P13: Relative Frequency | Q13: Cumulative Frequency | R13: Cumulative Relative Frequency
A14: West Gear | B14: 1185732 | C14: 44358 | D14: West | E14: Utah | F14: Salt Lake City | G14: Women's Street Footwear | H14: 20 | I14: 425 | J14: 8500 | K14: 2975 | L14: In-store | N14: {=_xlfn.UNIQUE(L2:L5000)} -> Online | O14: =COUNTIF(L2:L5000,"Online") -> 2867 | P14: =O14/SUM($O$14:$O$16) -> 0.5735147 | Q14: =O14 -> 2867 | R14: =Q14/Q16 -> 0.5735147
A15: Amazon | B15: 1185732 | C15: 44296 | D15: Midwest | E15: Ohio | F15: Columbus | G15: Women's Street Footwear | H15: 20 | I15: 425 | J15: 8500 | K15: 3400 | L15: Online | N15: Outlet | O15: =COUNTIF(L2:L5000,"Outlet") -> 1735 | P15: =O15/SUM($O$14:$O$16) -> 0.34706941 | Q15: =O14+O15 -> 4602 | R15: =Q15/Q16 -> 0.92058412
A16: Foot Locker | B16: 1185732 | C16: 44271 | D16: South | E16: Mississippi | F16: Jackson | G16: Women's Street Footwear | H16: 15 | I16: 425 | J16: 6375 | K16: 2550 | L16: Online | N16: In-store | O16: =COUNTIF(L2:L5000,"In-store") -> 397 | P16: =O16/SUM($O$14:$O$16) -> 0.079415883 | Q16: =O14+O15+O16 -> 4999 | R16: =Q16/Q16 -> 1
A17: Walmart | B17: 1185732 | C17: 44455 | D17: South | E17: Mississippi | F17: Jackson | G17: Women's Street Footwear | H17: 20 | I17: 425 | J17: 8500 | K17: 3400 | L17: Online
A18: Walmart | B18: 1197831 | C18: 44248 | D18: South | E18: Arkansas | F18: Little Rock | G18: Women's Apparel | H18: 20 | I18: 425 | J18: 8500 | K18: 3400 | L18: Online
A19: Walmart | B19: 1197831 | C19: 44490 | D19: South | E19: Arkansas | F19: Little Rock | G19: Men's Athletic Footwear | H19: 20 | I19: 425 | J19: 8500 | K19: 2975 | L19: Online
A20: Walmart | B20: 1185732 | C20: 43954 | D20: Northeast | E20: New York | F20: New York | G20: Men's Street Footwear | H20: 48 | I20: 420 | J20: 2016 | K20: 1129 | L20: Outlet
A21: Walmart | B21: 1185732 | C21: 43940 | D21: Northeast | E21: New York | F21: New York | G21: Men's Street Footwear | H21: 39 | I21: 408 | J21: 1591 | K21: 875 | L21: Outlet
A22: Walmart | B22: 1185732 | C22: 43948 | D22: Northeast | E22: New York | F22: New York | G22: Men's Street Footwear | H22: 46 | I22: 403 | J22: 1854 | K22: 1038 | L22: Outlet
A23: West Gear | B23: 1185732 | C23: 44265 | D23: West | E23: Utah | F23: Salt Lake City | G23: Women's Street Footwear | H23: 20 | I23: 400 | J23: 8000 | K23: 2800 | L23: In-store
A24: West Gear | B24: 1185732 | C24: 44358 | D24: West | E24: Utah | F24: Salt Lake City | G24: Women's Athletic Footwear | H24: 20 | I24: 400 | J24: 8000 | K24: 3200 | L24: In-store
A25: West Gear | B25: 1185732 | C25: 44480 | D25: West | E25: Utah | F25: Salt Lake City | G25: Men's Athletic Footwear | H25: 20 | I25: 400 | J25: 8000 | K25: 2800 | L25: In-store
A26: West Gear | B26: 1185732 | C26: 44511 | D26: West | E26: Utah | F26: Salt Lake City | G26: Men's Athletic Footwear | H26: 20 | I26: 400 | J26: 8000 | K26: 2800 | L26: In-store
A27: Walmart | B27: 1185732 | C27: 44455 | D27: South | E27: Mississippi | F27: Jackson | G27: Women's Athletic Footwear | H27: 20 | I27: 400 | J27: 8000 | K27: 3200 | L27: Online
A28: Sports Direct | B28: 1197831 | C28: 44248 | D28: South | E28: Mississippi | F28: Jackson | G28: Women's Street Footwear | H28: 15 | I28: 400 | J28: 6000 | K28: 2400 | L28: Online
... A5000: Amazon | B5000: 1185732 | C5000: 44540 | D5000: Northeast | E5000: Vermont | F5000: Burlington | G5000: Women's Athletic Footwear | H5000: 56 | I5000: 81 | J5000: 454 | K5000: 204 | L5000: Online

Sheet 1. Dataset and task decription

Sheet 2.1.2 Descriptive Analytics
A2: Average of Operating Profit | B2: Total Sales
A3: Region | B3: 58-2057 | C3: 2058-4057 | D3: 4058-6057 | E3: 6058-8057 | F3: 8058-10057 | G3: Grand Total
A4: Midwest | B4: 286.5617 | C4: 1133.3333 | D4: 1846.6733 | E4: 2540.064 | F4: 3152.0441 | G4: 1117.4845
A5: Northeast | B5: 328.69114 | C5: 1256.9 | D5: 1800.5915 | E5: 2438.8125 | F5: 2947.2059 | G5: 733.67433
A6: South | B6: 319.19293 | C6: 1303.7692 | D6: 2003.8 | E6: 2800.2917 | F6: 3352.5714 | G6: 476.85841
A7: Southeast | B7: 397.089 | C7: 1215 | D7: 2066.6667 | E7: 2743.3333 | F7: 3077 | G7: 500.53846
A8: West | B8: 316.93109 | C8: 1262.5 | D8: 2107 | E8: 2468.087 | F8: 2782 | G8: 384.54578
A9: Grand Total | B9: 327.8713 | C9: 1187.8784 | D9: 1865.91 | E9: 2532.7102 | F9: 3097.6831 | G9: 609.0174

Sheet 2.2.Numerical Variables
A1: Table 2.2.1 (Numerical Variables – Summary Statistics)
A2: Variable | B2: Min | C2: Q1(25%) | D2: Q2(Median) | E2: Q3 (75%) | F2: Q4 (Max) | G2: Mean
A3: Total Sales | B3: =MIN('Raw Data& 2.1.1'!J2:J5000) -> 58 | C3: =_xlfn.QUARTILE.INC('Raw Data& 2.1.1'!J2:J5000,1) -> 470 | D3: =MEDIAN('Raw Data& 2.1.1'!J2:J5000) -> 704 | E3: =_xlfn.QUARTILE.INC('Raw Data& 2.1.1'!J2:J5000,3) -> 1136.5 | F3: =MAX('Raw Data& 2.1.1'!J2:J5000) -> 9000 | G3: =AVERAGE('Raw Data& 2.1.1'!J2:J5000) -> 1531.0204
A4: Operating Profit | B4: =MIN('Raw Data& 2.1.1'!K2:K5000) -> 26 | C4: =_xlfn.QUARTILE.INC('Raw Data& 2.1.1'!K2:K5000,1) -> 212 | D4: =MEDIAN('Raw Data& 2.1.1'!K2:K5000) -> 322 | E4: =_xlfn.QUARTILE.INC('Raw Data& 2.1.1'!K2:K5000,3) -> 534 | F4: =MAX('Raw Data& 2.1.1'!K2:K5000) -> 5400 | G4: =AVERAGE('Raw Data& 2.1.1'!K2:K5000) -> 609.0174
A5: Units Sold | B5: =MIN('Raw Data& 2.1.1'!I2:I5000) -> 81 | C5: =_xlfn.QUARTILE.INC('Raw Data& 2.1.1'!I2:I5000,1) -> 119 | D5: =MEDIAN('Raw Data& 2.1.1'!I2:I5000) -> 150 | E5: =_xlfn.QUARTILE.INC('Raw Data& 2.1.1'!I2:I5000,3) -> 200 | F5: =MAX('Raw Data& 2.1.1'!I2:I5000) -> 700 | G5: =AVERAGE('Raw Data& 2.1.1'!I2:I5000) -> 165.39428
A6: Price per Unit | B6: =MIN('Raw Data& 2.1.1'!H2:H5000) -> 7 | C6: =_xlfn.QUARTILE.INC('Raw Data& 2.1.1'!H2:H5000,1) -> 33 | D6: =MEDIAN('Raw Data& 2.1.1'!H2:H5000) -> 42 | E6: =_xlfn.QUARTILE.INC('Raw Data& 2.1.1'!H2:H5000,3) -> 52 | F6: =MAX('Raw Data& 2.1.1'!H2:H5000) -> 103 | G6: =AVERAGE('Raw Data& 2.1.1'!H2:H5000) -> 42.74975

Sheet 2.2.3. Box Plot
D18: Box Plot 1:Table Sales | L18: Box Plot 2: Operating Profit
D19: Q1 | E19: 470 | L19: Q1 | M19: ='2.2.Numerical Variables'!C4 -> 212
D20: Q3 | E20: =_xlfn.QUARTILE.INC('Raw Data& 2.1.1'!J2:J5000,3) -> 1136.5 | L20: Q3 | M20: ='2.2.Numerical Variables'!E4 -> 534
D21: IQR | E21: =E20-E19 -> 666.5 | L21: IQR | M21: =M20-M19 -> 322
D22: Lower | E22: =E19-1.5*E21 -> -529.75 | L22: Lower | M22: =M19-1.5*M21 -> -271
D23: Upper | E23: =E20+1.5*E21 -> 2136.25 | L23: Upper | M23: =M20+1.5*M21 -> 1017
D24: Range | E24: ='2.2.Numerical Variables'!F3-'2.2.Numerical Variables'!B3 -> 8942 | L24: Range | M24: ='2.2.Numerical Variables'!F4-'2.2.Numerical Variables'!B4 -> 5374

Sheet 3.Simple Linear Regression
K3: Statistic | M3: Value | O3: Interpretation
K4: Equation | M4: y = 0.3447x + 81.298 | O4: Linear relationship between profit and sales
K5: R² | M5: 0.9493 | O5: 94.93% of sales variation explained by profit
K6: Correlation (r) | M6: =CORREL('Raw Data& 2.1.1'!K2:K5000,'Raw Data& 2.1.1'!J2:J5000) -> 0.97433936 | O6: Strong positive linear relationship
K7: Slope | M7: 0.3447 | O7: For every $1 increase in sales, profit rise by $0.3447
K8: Intercept | M8: 81.298 | O8: When sales = 0, predicted profit ≈ $81
